{
  "logging": {
    "level": "info",
    "console": "false",
    "syslog": {
      "enable": "true"
    }
  },
  "routing": "someipd",
  "services": [
    {
      "service": "3",
      "instance": "10013",
      "is_signal": "false",
      "reliable": "0",
      "events": [
        {
          "event": "1"
        }
      ],
      "eventgroups": [
        {
          "eventgroup": "2",
          "events": []
        }
      ]
    },
    {
      "service": "3",
      "instance": "10014",
      "is_signal": "false",
      "reliable": "0",
      "events": [
        {
          "event": "1"
        }
      ],
      "eventgroups": [
        {
          "eventgroup": "2",
          "events": []
        }
      ]
    },
    {
      "service": "3",
      "instance": "10016",
      "is_signal": "false",
      "reliable": "0",
      "events": [
        {
          "event": "1"
        }
      ],
      "eventgroups": [
        {
          "eventgroup": "2",
          "events": []
        }
      ]
    }
  ],
  "clients": [
    {
      "service": "1100",
      "instance": "10009",
      "is_signal": "false",
      "reliable": [
        "0"
      ],
      "events": [
        {
          "event": "1"
        }
      ]
    }
  ]
}