{
  "applicationName": "/HuaweiMDC/Common/Common/around_view_camera_perception_libCompositionSwComponentType7/around_view_camera_perception_libProcess7",
  "services": [
    {
      "service": "/HuaweiMDC/interface_manifests/interfaces/CameraStructContainerInterface",
      "serviceId": 2,
      "events": [
        {
          "event": "event",
          "id": 31614,
          "isDpRawData": true,
          "dataType": "/HuaweiMDC/CameraStructContainer",
          "topicName": "TopicOfevent"
        }
      ],
      "fields": [],
      "methods": [],
      "instances": [
        {
          "shortName": "/HuaweiMDC/instance_manifests/requiredInstances/IflytekSensorCameraSurroundResizeImageFront_DdsRequiredServiceInstance20",
          "instance": "10023",
          "vlan": "InnerEthernetPhysicalChannel",
          "domainId": 30,
          "network": "192.168.10.6",
          "isClient": true,
          "qosProfile": "small_buffer_qos.xml",
          "events": [
            {
              "id": 31614,
              "dataIds": []
            }
          ],
          "fields": [],
          "methods": []
        },
        {
          "shortName": "/HuaweiMDC/instance_manifests/requiredInstances/IflytekSensorCameraSurroundResizeImageLeft_DdsRequiredServiceInstance21",
          "instance": "10024",
          "vlan": "InnerEthernetPhysicalChannel",
          "domainId": 30,
          "network": "192.168.10.6",
          "isClient": true,
          "qosProfile": "small_buffer_qos.xml",
          "events": [
            {
              "id": 31614,
              "dataIds": []
            }
          ],
          "fields": [],
          "methods": []
        },
        {
          "shortName": "/HuaweiMDC/instance_manifests/requiredInstances/IflytekSensorCameraSurroundResizeImageRear_DdsRequiredServiceInstance23",
          "instance": "10042",
          "vlan": "InnerEthernetPhysicalChannel",
          "domainId": 30,
          "network": "192.168.10.6",
          "isClient": true,
          "qosProfile": "small_buffer_qos.xml",
          "events": [
            {
              "id": 31614,
              "dataIds": []
            }
          ],
          "fields": [],
          "methods": []
        },
        {
          "shortName": "/HuaweiMDC/instance_manifests/requiredInstances/IflytekSensorCameraSurroundResizeImageRight_DdsRequiredServiceInstance22",
          "instance": "10041",
          "vlan": "InnerEthernetPhysicalChannel",
          "domainId": 30,
          "network": "192.168.10.6",
          "isClient": true,
          "qosProfile": "small_buffer_qos.xml",
          "events": [
            {
              "id": 31614,
              "dataIds": []
            }
          ],
          "fields": [],
          "methods": []
        }
      ]
    },
    {
      "service": "/HuaweiMDC/interface_manifests/interfaces/StructContainerInterface",
      "serviceId": 1,
      "events": [
        {
          "event": "event",
          "id": 31614,
          "isDpRawData": false,
          "dataType": "/HuaweiMDC/PlatformServices/DiagMsgDataType/DataTypes/ByteVector",
          "topicName": "TopicOfevent"
        }
      ],
      "fields": [],
      "methods": [],
      "instances": [
        {
          "shortName": "/HuaweiMDC/instance_manifests/providedInstances/IflytekCameraPerception3dGeneralObjects_DdsProvidedServiceInstance8",
          "instance": "10043",
          "vlan": "InnerEthernetPhysicalChannel",
          "domainId": 30,
          "network": "192.168.10.6",
          "isClient": false,
          "qosProfile": "customized_qos.xml",
          "events": [
            {
              "id": 31614,
              "dataIds": []
            }
          ],
          "fields": [],
          "methods": []
        },
        {
          "shortName": "/HuaweiMDC/instance_manifests/providedInstances/IflytekCameraPerception3dOccupancyObjects_DdsProvidedServiceInstance44",
          "instance": "10212",
          "vlan": "InnerEthernetPhysicalChannel",
          "domainId": 30,
          "network": "192.168.10.6",
          "isClient": false,
          "qosProfile": "large_buffer_qos.xml",
          "events": [
            {
              "id": 31614,
              "dataIds": []
            }
          ],
          "fields": [],
          "methods": []
        },
        {
          "shortName": "/HuaweiMDC/instance_manifests/providedInstances/IflytekCameraPerceptionAroundPhmReport_DdsProvidedAroundViewCameraPerception",
          "instance": "10207",
          "vlan": "InnerEthernetPhysicalChannel",
          "domainId": 30,
          "network": "192.168.10.6",
          "isClient": false,
          "qosProfile": "small_buffer_qos.xml",
          "events": [
            {
              "id": 31614,
              "dataIds": []
            }
          ],
          "fields": [],
          "methods": []
        },
        {
          "shortName": "/HuaweiMDC/instance_manifests/providedInstances/IflytekCameraPerceptionAroundView2DBoundingBoxes_DdsProvidedServiceInstance37",
          "instance": "10188",
          "vlan": "InnerEthernetPhysicalChannel",
          "domainId": 30,
          "network": "192.168.10.6",
          "isClient": false,
          "qosProfile": "customized_qos.xml",
          "events": [
            {
              "id": 31614,
              "dataIds": []
            }
          ],
          "fields": [],
          "methods": []
        },
        {
          "shortName": "/HuaweiMDC/instance_manifests/providedInstances/IflytekCameraPerceptionDeceler_DdsProvidedServiceInstance14",
          "instance": "10079",
          "vlan": "InnerEthernetPhysicalChannel",
          "domainId": 30,
          "network": "192.168.10.6",
          "isClient": false,
          "qosProfile": "small_buffer_qos.xml",
          "events": [
            {
              "id": 31614,
              "dataIds": []
            }
          ],
          "fields": [],
          "methods": []
        },
        {
          "shortName": "/HuaweiMDC/instance_manifests/providedInstances/IflytekCameraPerceptionGroundLine_DdsProvidedServiceInstance12",
          "instance": "10065",
          "vlan": "InnerEthernetPhysicalChannel",
          "domainId": 30,
          "network": "192.168.10.6",
          "isClient": false,
          "qosProfile": "customized_qos.xml",
          "events": [
            {
              "id": 31614,
              "dataIds": []
            }
          ],
          "fields": [],
          "methods": []
        },
        {
          "shortName": "/HuaweiMDC/instance_manifests/providedInstances/IflytekCameraPerceptionOccupancyObjects_DdsProvidedServiceInstance9",
          "instance": "10044",
          "vlan": "InnerEthernetPhysicalChannel",
          "domainId": 30,
          "network": "192.168.10.6",
          "isClient": false,
          "qosProfile": "large_buffer_qos.xml",
          "events": [
            {
              "id": 31614,
              "dataIds": []
            }
          ],
          "fields": [],
          "methods": []
        },
        {
          "shortName": "/HuaweiMDC/instance_manifests/providedInstances/IflytekCameraPerceptionParkingLaneLine_DdsProvidedServiceInstance13",
          "instance": "10074",
          "vlan": "InnerEthernetPhysicalChannel",
          "domainId": 30,
          "network": "192.168.10.6",
          "isClient": false,
          "qosProfile": "customized_qos.xml",
          "events": [
            {
              "id": 31614,
              "dataIds": []
            }
          ],
          "fields": [],
          "methods": []
        },
        {
          "shortName": "/HuaweiMDC/instance_manifests/providedInstances/IflytekCameraPerceptionParkingSlotList_DdsProvidedServiceInstance11",
          "instance": "10014",
          "vlan": "InnerEthernetPhysicalChannel",
          "domainId": 30,
          "network": "192.168.10.6",
          "isClient": false,
          "qosProfile": "default_qos.xml",
          "events": [
            {
              "id": 31614,
              "dataIds": []
            }
          ],
          "fields": [],
          "methods": []
        },
        {
          "shortName": "/HuaweiMDC/instance_manifests/requiredInstances/IflytekFsmSocState_DdsRequiredServiceInstance47",
          "instance": "10110",
          "vlan": "InnerEthernetPhysicalChannel",
          "domainId": 30,
          "network": "192.168.10.6",
          "isClient": true,
          "qosProfile": "small_buffer_qos.xml",
          "events": [
            {
              "id": 31614,
              "dataIds": []
            }
          ],
          "fields": [],
          "methods": []
        },
        {
          "shortName": "/HuaweiMDC/instance_manifests/requiredInstances/IflytekLocalizationEgomotion_DdsRequiredServiceInstance47",
          "instance": "10083",
          "vlan": "InnerEthernetPhysicalChannel",
          "domainId": 30,
          "network": "192.168.10.6",
          "isClient": true,
          "qosProfile": "small_buffer_qos.xml",
          "events": [
            {
              "id": 31614,
              "dataIds": []
            }
          ],
          "fields": [],
          "methods": []
        },
        {
          "shortName": "/HuaweiMDC/instance_manifests/requiredInstances/IflytekUssUsswaveInfo_DdsRequiredServiceInstance47",
          "instance": "10018",
          "vlan": "InnerEthernetPhysicalChannel",
          "domainId": 30,
          "network": "192.168.10.6",
          "isClient": true,
          "qosProfile": "small_buffer_qos.xml",
          "events": [
            {
              "id": 31614,
              "dataIds": []
            }
          ],
          "fields": [],
          "methods": []
        },
        {
          "shortName": "/HuaweiMDC/instance_manifests/requiredInstances/IflytekVehicleService_DdsRequiredServiceInstance47",
          "instance": "10009",
          "vlan": "InnerEthernetPhysicalChannel",
          "domainId": 30,
          "network": "192.168.10.6",
          "isClient": true,
          "qosProfile": "small_buffer_qos.xml",
          "events": [
            {
              "id": 31614,
              "dataIds": []
            }
          ],
          "fields": [],
          "methods": []
        }
      ]
    }
  ]
}